arena/__init__.py
arena/auth.py
arena/common.py
arena/config.py
arena/login.py
arena/main.py
arena/request.py
arena/set_host.py
arena/submission.py
arena/token.py
arena/urls.py
arena/version.py
arena_cli-1.7.dist-info/LICENSE
arena_cli-1.7.dist-info/METADATA
arena_cli-1.7.dist-info/WHEEL
arena_cli-1.7.dist-info/entry_points.txt
arena_cli-1.7.dist-info/top_level.txt
arena_cli-1.7.dist-info/RECORD
